csvg/__init__.py
csvg/canvas.py
csvg/circle.py
csvg/data_matrix.py
csvg/element.py
csvg/image.py
csvg/lib.py
csvg/line.py
csvg/qr_code.py
csvg/rectangle.py
csvg/svg.py
csvg/text.py
csvg-0.1.1.dist-info/LICENSE
csvg-0.1.1.dist-info/METADATA
csvg-0.1.1.dist-info/WHEEL
csvg-0.1.1.dist-info/top_level.txt
csvg-0.1.1.dist-info/RECORD
