Metadata-Version: 2.1
Name: csvg
Version: 0.1.1
Summary: (C)onstraint (S)olved (V)ector (G)raphics
Author-email: csvg <fredrik@atmer.se>
License: GNU GENERAL PUBLIC LICENSE
Project-URL: Homepage, https://github.com/BathroomEpiphanies/python3-csvg
Keywords: csvg
Classifier: License :: OSI Approved :: GNU General Public License v3 (GPLv3)
Classifier: Programming Language :: Python :: 3
Requires-Python: >=3.11
License-File: LICENSE
Provides-Extra: dev
Requires-Dist: pip-tools ; extra == 'dev'
Requires-Dist: pytest ; extra == 'dev'
